lawfirm_rag/__init__.py
lawfirm_rag/api/__init__.py
lawfirm_rag/api/fastapi_app.py
lawfirm_rag/cli/__init__.py
lawfirm_rag/cli/analyze.py
lawfirm_rag/cli/env_manager.py
lawfirm_rag/cli/main.py
lawfirm_rag/cli/query.py
lawfirm_rag/cli/server.py
lawfirm_rag/core/__init__.py
lawfirm_rag/core/ai_engine.py
lawfirm_rag/core/document_processor.py
lawfirm_rag/core/embeddings.py
lawfirm_rag/core/enhanced_document_processor.py
lawfirm_rag/core/exceptions.py
lawfirm_rag/core/llm_backend.py
lawfirm_rag/core/model_downloader.py
lawfirm_rag/core/model_manager.py
lawfirm_rag/core/ollama_client.py
lawfirm_rag/core/query_generator.py
lawfirm_rag/core/vector_store.py
lawfirm_rag/utils/__init__.py
lawfirm_rag/utils/config.py
lawfirm_rag/utils/file_handlers.py
lawfirm_rag/utils/migration.py
lawfirm_rag/utils/setup.py
lawfirm_rag/web/__init__.py
lawfirm_rag/web/static/index.html
lawfirm_rag/web/static/assets/app.js
lawfirm_rag/web/static/assets/styles.css
lawfirm_rag/web/static/assets/modules/ApiClient.js
lawfirm_rag/web/static/assets/modules/DocumentAnalyzer.js
lawfirm_rag/web/static/assets/modules/FileHandler.js
lawfirm_rag/web/static/assets/modules/ModelManager.js
lawfirm_rag/web/static/assets/modules/UIManager.js
lawfirm_rag/web/templates/vector_test.html
rag_package-0.1.9.dist-info/licenses/LICENSE
rag_package-0.1.9.dist-info/METADATA
rag_package-0.1.9.dist-info/WHEEL
rag_package-0.1.9.dist-info/entry_points.txt
rag_package-0.1.9.dist-info/top_level.txt
rag_package-0.1.9.dist-info/RECORD
