Metadata-Version: 2.4
Name: rag-package
Version: 0.1.9
Summary: AI-powered document analysis and query generation tool with RAG capabilities
Author-email: DannyMExe <dannyjmargolin@gmail.com>
Maintainer-email: DannyMExe <dannyjmargolin@gmail.com>
License: Evaluation License
Project-URL: Homepage, https://github.com/DannyMExe/rag-package
Project-URL: Documentation, https://lawfirm-rag.readthedocs.io
Project-URL: Repository, https://github.com/DannyMExe/rag-package
Project-URL: Bug Tracker, https://github.com/DannyMExe/rag-package/issues
Project-URL: Changelog, https://github.com/DannyMExe/rag-package/blob/main/CHANGELOG.md
Keywords: legal,ai,document-analysis,rag,llm,legal-research,query-generation,legal-tech,nlp,document-processing
Classifier: Development Status :: 3 - Alpha
Classifier: Intended Audience :: Legal Industry
Classifier: Intended Audience :: Developers
Classifier: License :: Other/Proprietary License
Classifier: Operating System :: OS Independent
Classifier: Programming Language :: Python :: 3
Classifier: Programming Language :: Python :: 3.11
Classifier: Topic :: Scientific/Engineering :: Artificial Intelligence
Classifier: Topic :: Text Processing :: Linguistic
Requires-Python: >=3.11
License-File: LICENSE
Requires-Dist: fastapi>=0.104.0
Requires-Dist: uvicorn[standard]>=0.24.0
Requires-Dist: python-multipart>=0.0.6
Requires-Dist: pydantic>=2.0.0
Requires-Dist: click>=8.0.0
Requires-Dist: requests>=2.31.0
Requires-Dist: python-docx>=0.8.11
Requires-Dist: PyPDF2>=3.0.0
Requires-Dist: psutil>=5.9.0
Requires-Dist: rich>=13.0.0
Requires-Dist: Jinja2>=3.1.0
Requires-Dist: PyYAML>=6.0
Requires-Dist: python-dotenv>=1.0.0
Requires-Dist: pdfplumber==0.9.0
Requires-Dist: PyMuPDF>=1.24.0
Requires-Dist: chromadb==0.4.15
Requires-Dist: numpy==1.24.3
Requires-Dist: sentence-transformers==4.1.0
Requires-Dist: torch==2.1.0+cpu
Requires-Dist: ollama==0.1.9
Requires-Dist: transformers==4.35.2
Requires-Dist: tokenizers==0.15.0
Requires-Dist: huggingface-hub==0.19.4
Provides-Extra: gguf
Requires-Dist: llama-cpp-python>=0.2.0; extra == "gguf"
Provides-Extra: dev
Requires-Dist: pytest>=7.0.0; extra == "dev"
Requires-Dist: pytest-cov>=4.0.0; extra == "dev"
Requires-Dist: pytest-asyncio>=0.21.0; extra == "dev"
Requires-Dist: black>=23.0.0; extra == "dev"
Requires-Dist: isort>=5.12.0; extra == "dev"
Requires-Dist: flake8>=6.0.0; extra == "dev"
Requires-Dist: mypy>=1.5.0; extra == "dev"
Requires-Dist: pre-commit>=3.0.0; extra == "dev"
Provides-Extra: web
Requires-Dist: jinja2>=3.1.0; extra == "web"
Requires-Dist: aiofiles>=23.0.0; extra == "web"
Provides-Extra: gui
Requires-Dist: streamlit>=1.28.0; extra == "gui"
Requires-Dist: gradio>=4.0.0; extra == "gui"
Provides-Extra: docs
Requires-Dist: sphinx>=7.0.0; extra == "docs"
Requires-Dist: sphinx-rtd-theme>=1.3.0; extra == "docs"
Requires-Dist: myst-parser>=2.0.0; extra == "docs"
Provides-Extra: all
Requires-Dist: lawfirm-rag[dev,docs,gui,web]; extra == "all"
Dynamic: license-file
